objexp/__init__.py
objexp/__main__.py
objexp-1.0.3.dist-info/LICENSE.txt
objexp-1.0.3.dist-info/METADATA
objexp-1.0.3.dist-info/WHEEL
objexp-1.0.3.dist-info/entry_points.txt
objexp-1.0.3.dist-info/top_level.txt
objexp-1.0.3.dist-info/RECORD
