Metadata-Version: 2.1
Name: objexp
Version: 1.0.3
Summary: List the members in a Object[also Class or Module].
Author-email: Luke Lin <luke.l.lin@hotmail.com>
Project-URL: Homepage, https://github.com/sunrenn/objexp
Keywords: dir,vars,debug
Classifier: License :: OSI Approved :: MIT License
Classifier: Programming Language :: Python
Classifier: Programming Language :: Python :: 3
Classifier: Development Status :: 4 - Beta
Classifier: Environment :: Win32 (MS Windows)
Classifier: Environment :: Console
Classifier: Natural Language :: Chinese (Simplified)
Classifier: Natural Language :: English
Classifier: Topic :: Software Development :: Documentation
Requires-Python: >=3.9
License-File: LICENSE.txt
